artii/__init__.py
artii/main.py
artii-1.0.1.dist-info/LICENSE
artii-1.0.1.dist-info/METADATA
artii-1.0.1.dist-info/WHEEL
artii-1.0.1.dist-info/entry_points.txt
artii-1.0.1.dist-info/top_level.txt
artii-1.0.1.dist-info/RECORD
