Metadata-Version: 2.1
Name: artii
Version: 1.0.1
Summary: A CLI tool to convert images, GIFs, and videos to ASCII
Home-page: https://github.com/migibert/artii
Author: Mikael Gibert
Author-email: 
Classifier: Programming Language :: Python :: 3
Classifier: License :: OSI Approved :: MIT License
Classifier: Operating System :: OS Independent
Requires-Python: >=3.6
License-File: LICENSE
Requires-Dist: opencv-python
